py_balcalc/__init__.py
py_balcalc/logger.py
py_balcalc/main.py
py_balcalc/settings.py
py_balcalc/signals_manager.py
py_balcalc/translator.py
py_balcalc/file/__init__.py
py_balcalc/file/file_worker.py
py_balcalc/resources/__init__.py
py_balcalc/resources/resources.py
py_balcalc/translations/English.json
py_balcalc/translations/Ukrainian.json
py_balcalc/ui/__init__.py
py_balcalc/ui/message_handler.py
py_balcalc/ui/stylesheet.py
py_balcalc/ui/calculator/__init__.py
py_balcalc/ui/calculator/calculator.py
py_balcalc/ui/calculator/conditions/__init__.py
py_balcalc/ui/calculator/conditions/conditions.py
py_balcalc/ui/calculator/table/__init__.py
py_balcalc/ui/calculator/table/drag_table.py
py_balcalc/ui/calculator/table/trajectory_table.py
py_balcalc/ui/custom_widgets/__init__.py
py_balcalc/ui/custom_widgets/no_wheel_sb.py
py_balcalc/ui/custom_widgets/spin_box_delegate.py
py_balcalc/ui/custom_widgets/t_label.py
py_balcalc/ui/custom_widgets/table_model.py
py_balcalc/ui/custom_widgets/unit_spin_box.py
py_balcalc/ui/custom_widgets/valid_line_edit.py
py_balcalc/ui/main_window/__init__.py
py_balcalc/ui/main_window/data_worker.py
py_balcalc/ui/main_window/footer.py
py_balcalc/ui/main_window/main_window.py
py_balcalc/ui/main_window/add_button/__init__.py
py_balcalc/ui/main_window/add_button/add_button.py
py_balcalc/ui/main_window/profile_a7p_meta/__init__.py
py_balcalc/ui/main_window/profile_a7p_meta/prof_a7p_meta.py
py_balcalc/ui/main_window/profile_bullet/__init__.py
py_balcalc/ui/main_window/profile_bullet/prof_bullet.py
py_balcalc/ui/main_window/profile_bullet/prof_drag_model/__init__.py
py_balcalc/ui/main_window/profile_bullet/prof_drag_model/prof_drag_model.py
py_balcalc/ui/main_window/profile_cartridge/__init__.py
py_balcalc/ui/main_window/profile_cartridge/prof_cartridge.py
py_balcalc/ui/main_window/profile_conditions/__init__.py
py_balcalc/ui/main_window/profile_conditions/prof_conditions.py
py_balcalc/ui/main_window/profile_tab/__init__.py
py_balcalc-0.0.1a8.dist-info/LICENSE
py_balcalc-0.0.1a8.dist-info/METADATA
py_balcalc-0.0.1a8.dist-info/WHEEL
py_balcalc-0.0.1a8.dist-info/entry_points.txt
py_balcalc-0.0.1a8.dist-info/top_level.txt
py_balcalc-0.0.1a8.dist-info/RECORD
