Metadata-Version: 2.1
Name: py-balcalc
Version: 0.0.1a8
Summary: PySide6 based GUI for the py_ballisticcalc library
Author-email: o-murphy <thehelixpg@gmail.com>
License: GNU GENERAL PUBLIC LICENSE
Project-URL: Homepage, https://github.com/o-murphy/py_balcalc
Project-URL: Bug Reports, https://github.com/o-murphy/py_balcalc/issues
Project-URL: Source, https://github.com/o-murphy/py_balcalc
Keywords: py_ballisticcalc,ballistics,Cython,ballistic calculator,python,python3
Classifier: Intended Audience :: Developers
Classifier: Natural Language :: English
Classifier: Programming Language :: Python
Classifier: Topic :: Software Development :: Libraries :: Python Modules
Classifier: Programming Language :: Python :: 3
Classifier: Programming Language :: Python :: 3 :: Only
Classifier: Programming Language :: Python :: 3.9
Classifier: Programming Language :: Python :: 3.10
Classifier: Programming Language :: Python :: 3.11
Classifier: Programming Language :: Python :: 3.12
Classifier: Operating System :: OS Independent
Classifier: Programming Language :: Python :: Implementation :: CPython
Requires-Python: >=3.9
License-File: LICENSE
Requires-Dist: PySide6 ~=6.6.0
Requires-Dist: pyqtgraph ==0.13.3
Requires-Dist: qtawesome ==1.2.3
Requires-Dist: py-ballisticcalc ==1.1.0
Requires-Dist: a7p ==0.0.8
Provides-Extra: exts
Requires-Dist: py-ballisticcalc.exts ; extra == 'exts'
